LICENSE
MANIFEST.in
README.html
README.rst
setup.cfg
setup.py
TracPiwik.egg-info/PKG-INFO
TracPiwik.egg-info/SOURCES.txt
TracPiwik.egg-info/dependency_links.txt
TracPiwik.egg-info/entry_points.txt
TracPiwik.egg-info/namespace_packages.txt
TracPiwik.egg-info/requires.txt
TracPiwik.egg-info/top_level.txt
tracext/__init__.py
tracext/piwik/__init__.py
tracext/piwik/admin.py
tracext/piwik/web_ui.py
tracext/piwik/htdocs/tracpiwik.css
tracext/piwik/templates/piwik.html
tracext/piwik/templates/piwik_admin.html