Metadata-Version: 1.0
Name: TracPiwik
Version: 0.1.1
Summary: Trac plugin to enable your trac environment to be logged by Piwik
Home-page: http://bitbucket.org/piquadrat/tracpiwik/
Author: Benjamin Wohlwend
Author-email: bw@piquadrat.ch
License: BSD
Download-URL: http://python.org/pypi/TracPiwik
Keywords: trac plugin piwik
Platform: UNKNOWN
Classifier: Framework :: Trac
